{
  "uid": "jobseek-crawler-pipeline",
  "title": "Crawler Pipeline",
  "schemaVersion": 39,
  "version": 3,
  "timezone": "browser",
  "editable": true,
  "graphTooltip": 1,
  "time": {
    "from": "now-6h",
    "to": "now"
  },
  "refresh": "30s",
  "templating": {
    "list": []
  },
  "annotations": {
    "list": []
  },
  "links": [],
  "panels": [
    {
      "id": 900,
      "type": "row",
      "title": "Reliability",
      "collapsed": false,
      "gridPos": {
        "h": 1,
        "w": 24,
        "x": 0,
        "y": 0
      },
      "panels": []
    },
    {
      "id": 901,
      "type": "stat",
      "title": "Scrape Targets Up",
      "datasource": {
        "type": "prometheus",
        "uid": "grafanacloud-prom"
      },
      "gridPos": {
        "h": 8,
        "w": 8,
        "x": 0,
        "y": 1
      },
      "fieldConfig": {
        "defaults": {
          "unit": "short",
          "thresholds": {
            "mode": "absolute",
            "steps": [
              {
                "color": "red",
                "value": null
              },
              {
                "color": "green",
                "value": 1
              }
            ]
          }
        },
        "overrides": []
      },
      "options": {
        "graphMode": "area",
        "orientation": "auto",
        "reduceOptions": {
          "calcs": [
            "lastNotNull"
          ],
          "fields": "",
          "values": false
        },
        "textMode": "auto",
        "colorMode": "value"
      },
      "targets": [
        {
          "refId": "A",
          "datasource": {
            "type": "prometheus",
            "uid": "grafanacloud-prom"
          },
          "expr": "up{job=\"crawler\"}",
          "legendFormat": "{{instance}}"
        }
      ]
    },
    {
      "id": 902,
      "type": "stat",
      "title": "External Deps",
      "datasource": {
        "type": "prometheus",
        "uid": "grafanacloud-prom"
      },
      "gridPos": {
        "h": 8,
        "w": 8,
        "x": 8,
        "y": 1
      },
      "fieldConfig": {
        "defaults": {
          "unit": "short",
          "thresholds": {
            "mode": "absolute",
            "steps": [
              {
                "color": "red",
                "value": null
              },
              {
                "color": "green",
                "value": 1
              }
            ]
          }
        },
        "overrides": []
      },
      "options": {
        "graphMode": "area",
        "orientation": "auto",
        "reduceOptions": {
          "calcs": [
            "lastNotNull"
          ],
          "fields": "",
          "values": false
        },
        "textMode": "auto",
        "colorMode": "value"
      },
      "targets": [
        {
          "refId": "A",
          "datasource": {
            "type": "prometheus",
            "uid": "grafanacloud-prom"
          },
          "expr": "crawler_typesense_healthy{instance=\"exporter\"}",
          "legendFormat": "Typesense"
        },
        {
          "refId": "B",
          "datasource": {
            "type": "prometheus",
            "uid": "grafanacloud-prom"
          },
          "expr": "crawler_redis_connected{instance=\"exporter\"}",
          "legendFormat": "Redis"
        }
      ]
    },
    {
      "id": 903,
      "type": "table",
      "title": "Build Info",
      "datasource": {
        "type": "prometheus",
        "uid": "grafanacloud-prom"
      },
      "gridPos": {
        "h": 8,
        "w": 8,
        "x": 16,
        "y": 1
      },
      "fieldConfig": {
        "defaults": {},
        "overrides": []
      },
      "options": {
        "showHeader": true,
        "cellHeight": "sm"
      },
      "targets": [
        {
          "refId": "A",
          "datasource": {
            "type": "prometheus",
            "uid": "grafanacloud-prom"
          },
          "expr": "crawler_build_info{job=\"crawler\"}",
          "instant": true,
          "format": "table",
          "legendFormat": ""
        }
      ],
      "transformations": [
        {
          "id": "organize",
          "options": {
            "excludeByName": {
              "Time": true,
              "__name__": true,
              "Value": true,
              "job": true
            },
            "renameByName": {
              "instance": "Instance",
              "version": "Version"
            }
          }
        }
      ]
    },
    {
      "id": 905,
      "type": "table",
      "title": "Worker Heartbeat Staleness",
      "datasource": {
        "type": "prometheus",
        "uid": "grafanacloud-prom"
      },
      "gridPos": {
        "h": 8,
        "w": 24,
        "x": 0,
        "y": 9
      },
      "fieldConfig": {
        "defaults": {
          "unit": "s",
          "thresholds": {
            "mode": "absolute",
            "steps": [
              {
                "color": "green",
                "value": null
              },
              {
                "color": "yellow",
                "value": 60
              },
              {
                "color": "red",
                "value": 600
              }
            ]
          },
          "custom": {
            "align": "auto",
            "cellOptions": {
              "type": "color-background"
            }
          }
        },
        "overrides": []
      },
      "options": {
        "showHeader": true,
        "cellHeight": "sm",
        "footer": {
          "show": false
        }
      },
      "targets": [
        {
          "refId": "A",
          "datasource": {
            "type": "prometheus",
            "uid": "grafanacloud-prom"
          },
          "expr": "time() - max by (instance, worker_id) (crawler_worker_heartbeat_timestamp_seconds)",
          "instant": true,
          "format": "table",
          "legendFormat": ""
        }
      ],
      "transformations": [
        {
          "id": "organize",
          "options": {
            "excludeByName": {
              "Time": true,
              "__name__": true,
              "job": true
            },
            "renameByName": {
              "instance": "Instance",
              "worker_id": "Worker",
              "Value": "Seconds since last heartbeat"
            }
          }
        }
      ],
      "description": "Seconds since each worker last updated `crawler_worker_heartbeat_timestamp_seconds`. Healthy workers tick every few seconds. >600s fires the WorkerStuck alert (page) \u2014 process is alive but the claim/dispatch loop has wedged (Playwright deadlock, scraper hang, etc.). See #3169."
    },
    {
      "id": 906,
      "type": "table",
      "title": "Cron Job Last Run",
      "datasource": {
        "type": "prometheus",
        "uid": "grafanacloud-prom"
      },
      "gridPos": {
        "h": 8,
        "w": 24,
        "x": 0,
        "y": 17
      },
      "fieldConfig": {
        "defaults": {
          "custom": {
            "align": "auto",
            "cellOptions": {
              "type": "auto"
            }
          },
          "thresholds": {
            "mode": "absolute",
            "steps": [
              {
                "color": "green",
                "value": null
              }
            ]
          }
        },
        "overrides": [
          {
            "matcher": {
              "id": "byName",
              "options": "Seconds since last run"
            },
            "properties": [
              {
                "id": "unit",
                "value": "s"
              },
              {
                "id": "custom.cellOptions",
                "value": {
                  "type": "color-background"
                }
              },
              {
                "id": "thresholds",
                "value": {
                  "mode": "absolute",
                  "steps": [
                    {
                      "color": "green",
                      "value": null
                    },
                    {
                      "color": "yellow",
                      "value": 14400
                    },
                    {
                      "color": "red",
                      "value": 21600
                    }
                  ]
                }
              }
            ]
          },
          {
            "matcher": {
              "id": "byName",
              "options": "Last status"
            },
            "properties": [
              {
                "id": "custom.cellOptions",
                "value": {
                  "type": "color-background"
                }
              },
              {
                "id": "mappings",
                "value": [
                  {
                    "type": "value",
                    "options": {
                      "0": {
                        "text": "failure",
                        "color": "red"
                      },
                      "1": {
                        "text": "success",
                        "color": "green"
                      }
                    }
                  }
                ]
              }
            ]
          }
        ]
      },
      "options": {
        "showHeader": true,
        "cellHeight": "sm",
        "footer": {
          "show": false
        }
      },
      "targets": [
        {
          "refId": "A",
          "datasource": {
            "type": "prometheus",
            "uid": "grafanacloud-prom"
          },
          "expr": "time() - max by (cron_job) (crawler_cron_last_run_ts)",
          "instant": true,
          "format": "table",
          "legendFormat": ""
        },
        {
          "refId": "B",
          "datasource": {
            "type": "prometheus",
            "uid": "grafanacloud-prom"
          },
          "expr": "max by (cron_job) (crawler_cron_last_run_status)",
          "instant": true,
          "format": "table",
          "legendFormat": ""
        }
      ],
      "transformations": [
        {
          "id": "merge",
          "options": {}
        },
        {
          "id": "organize",
          "options": {
            "excludeByName": {
              "Time": true,
              "__name__": true,
              "job": true
            },
            "indexByName": {
              "cron_job": 0,
              "Value #A": 1,
              "Value #B": 2
            },
            "renameByName": {
              "cron_job": "Cron job",
              "Value #A": "Seconds since last run",
              "Value #B": "Last status"
            }
          }
        }
      ],
      "description": "Per-cron last-run telemetry from `crawler_cron_last_run_ts` and `crawler_cron_last_run_status` (#2704). >6h since last run fires the CronJobMissing alert (page); `status=0` fires CronJobFailing (email). Requires CRAWLER_PUSHGATEWAY_URL to be set in the cron's runtime env; table is empty until then. See #3167."
    },
    {
      "id": 1,
      "type": "row",
      "title": "HTTP Worker",
      "collapsed": false,
      "gridPos": {
        "h": 1,
        "w": 24,
        "x": 0,
        "y": 25
      },
      "panels": []
    },
    {
      "id": 2,
      "type": "timeseries",
      "title": "Task Throughput \u2014 HTTP",
      "datasource": {
        "type": "prometheus",
        "uid": "grafanacloud-prom"
      },
      "gridPos": {
        "h": 8,
        "w": 9,
        "x": 0,
        "y": 26
      },
      "fieldConfig": {
        "defaults": {
          "unit": "short",
          "custom": {
            "fillOpacity": 10,
            "lineWidth": 2,
            "spanNulls": true
          },
          "color": {
            "mode": "palette-classic"
          }
        },
        "overrides": [
          {
            "matcher": {
              "id": "byRegexp",
              "options": "monitor-succeeded"
            },
            "properties": [
              {
                "id": "color",
                "value": {
                  "fixedColor": "green",
                  "mode": "fixed"
                }
              }
            ]
          },
          {
            "matcher": {
              "id": "byRegexp",
              "options": "scrape-succeeded"
            },
            "properties": [
              {
                "id": "color",
                "value": {
                  "fixedColor": "blue",
                  "mode": "fixed"
                }
              }
            ]
          },
          {
            "matcher": {
              "id": "byRegexp",
              "options": "monitor-failed"
            },
            "properties": [
              {
                "id": "color",
                "value": {
                  "fixedColor": "red",
                  "mode": "fixed"
                }
              }
            ]
          },
          {
            "matcher": {
              "id": "byRegexp",
              "options": "scrape-failed"
            },
            "properties": [
              {
                "id": "color",
                "value": {
                  "fixedColor": "orange",
                  "mode": "fixed"
                }
              }
            ]
          }
        ]
      },
      "options": {
        "legend": {
          "displayMode": "table",
          "calcs": [
            "last"
          ]
        },
        "tooltip": {
          "mode": "multi"
        }
      },
      "targets": [
        {
          "refId": "A",
          "datasource": {
            "type": "prometheus",
            "uid": "grafanacloud-prom"
          },
          "expr": "sum by (kind, status) (rate(crawler_tasks_total{instance=~\"worker-.*\"}[$__rate_interval])) * 60",
          "legendFormat": "{{kind}}-{{status}}"
        }
      ],
      "description": "Monitors and scrapes completed per minute by HTTP workers (worker-1/2/3). Green=monitor success, blue=scrape success, red/orange=failures."
    },
    {
      "id": 3,
      "type": "stat",
      "title": "Success Rate \u2014 HTTP",
      "datasource": {
        "type": "prometheus",
        "uid": "grafanacloud-prom"
      },
      "gridPos": {
        "h": 8,
        "w": 6,
        "x": 9,
        "y": 26
      },
      "fieldConfig": {
        "defaults": {
          "unit": "percentunit",
          "thresholds": {
            "mode": "absolute",
            "steps": [
              {
                "color": "red",
                "value": null
              },
              {
                "color": "yellow",
                "value": 0.8
              },
              {
                "color": "green",
                "value": 0.9
              }
            ]
          }
        },
        "overrides": []
      },
      "options": {
        "graphMode": "area",
        "orientation": "auto",
        "textMode": "auto",
        "colorMode": "value"
      },
      "targets": [
        {
          "refId": "A",
          "datasource": {
            "type": "prometheus",
            "uid": "grafanacloud-prom"
          },
          "expr": "sum(rate(crawler_tasks_total{instance=~\"worker-.*\", status=\"succeeded\"}[5m])) / sum(rate(crawler_tasks_total{instance=~\"worker-.*\"}[5m]))",
          "legendFormat": "Success Rate"
        }
      ],
      "description": "Percentage of tasks that succeed across all HTTP workers. Healthy: >95%."
    },
    {
      "id": 4,
      "type": "timeseries",
      "title": "Jobs Discovered \u2014 HTTP",
      "datasource": {
        "type": "prometheus",
        "uid": "grafanacloud-prom"
      },
      "gridPos": {
        "h": 8,
        "w": 9,
        "x": 15,
        "y": 26
      },
      "fieldConfig": {
        "defaults": {
          "unit": "short",
          "custom": {
            "fillOpacity": 10,
            "lineWidth": 2,
            "spanNulls": true
          },
          "color": {
            "mode": "palette-classic"
          }
        },
        "overrides": []
      },
      "options": {
        "legend": {
          "displayMode": "table",
          "calcs": [
            "last"
          ]
        },
        "tooltip": {
          "mode": "multi"
        }
      },
      "targets": [
        {
          "refId": "A",
          "datasource": {
            "type": "prometheus",
            "uid": "grafanacloud-prom"
          },
          "expr": "sum by (action) (rate(crawler_monitor_jobs_discovered_total{instance=~\"worker-.*\"}[$__rate_interval])) * 60",
          "legendFormat": "{{action}}"
        }
      ],
      "description": "New, relisted, and gone job postings detected per minute by HTTP monitors. Spikes when boards with many listings are checked."
    },
    {
      "id": 5,
      "type": "row",
      "title": "Browser Worker",
      "collapsed": false,
      "gridPos": {
        "h": 1,
        "w": 24,
        "x": 0,
        "y": 34
      },
      "panels": []
    },
    {
      "id": 6,
      "type": "timeseries",
      "title": "Task Throughput \u2014 Browser",
      "datasource": {
        "type": "prometheus",
        "uid": "grafanacloud-prom"
      },
      "gridPos": {
        "h": 8,
        "w": 9,
        "x": 0,
        "y": 35
      },
      "fieldConfig": {
        "defaults": {
          "unit": "short",
          "custom": {
            "fillOpacity": 10,
            "lineWidth": 2,
            "spanNulls": true
          },
          "color": {
            "mode": "palette-classic"
          }
        },
        "overrides": [
          {
            "matcher": {
              "id": "byRegexp",
              "options": "monitor-succeeded"
            },
            "properties": [
              {
                "id": "color",
                "value": {
                  "fixedColor": "green",
                  "mode": "fixed"
                }
              }
            ]
          },
          {
            "matcher": {
              "id": "byRegexp",
              "options": "scrape-succeeded"
            },
            "properties": [
              {
                "id": "color",
                "value": {
                  "fixedColor": "blue",
                  "mode": "fixed"
                }
              }
            ]
          },
          {
            "matcher": {
              "id": "byRegexp",
              "options": "monitor-failed"
            },
            "properties": [
              {
                "id": "color",
                "value": {
                  "fixedColor": "red",
                  "mode": "fixed"
                }
              }
            ]
          },
          {
            "matcher": {
              "id": "byRegexp",
              "options": "scrape-failed"
            },
            "properties": [
              {
                "id": "color",
                "value": {
                  "fixedColor": "orange",
                  "mode": "fixed"
                }
              }
            ]
          }
        ]
      },
      "options": {
        "legend": {
          "displayMode": "table",
          "calcs": [
            "last"
          ]
        },
        "tooltip": {
          "mode": "multi"
        }
      },
      "targets": [
        {
          "refId": "A",
          "datasource": {
            "type": "prometheus",
            "uid": "grafanacloud-prom"
          },
          "expr": "sum by (kind, status) (rate(crawler_tasks_total{instance=\"browser-1\"}[$__rate_interval])) * 60",
          "legendFormat": "{{kind}}-{{status}}"
        }
      ],
      "description": "Same as HTTP but for browser worker (Playwright/Chromium). Lower throughput is expected \u2014 each task launches a headless browser."
    },
    {
      "id": 7,
      "type": "stat",
      "title": "Success Rate \u2014 Browser",
      "datasource": {
        "type": "prometheus",
        "uid": "grafanacloud-prom"
      },
      "gridPos": {
        "h": 8,
        "w": 6,
        "x": 9,
        "y": 35
      },
      "fieldConfig": {
        "defaults": {
          "unit": "percentunit",
          "thresholds": {
            "mode": "absolute",
            "steps": [
              {
                "color": "red",
                "value": null
              },
              {
                "color": "yellow",
                "value": 0.8
              },
              {
                "color": "green",
                "value": 0.9
              }
            ]
          }
        },
        "overrides": []
      },
      "options": {
        "graphMode": "area",
        "orientation": "auto",
        "textMode": "auto",
        "colorMode": "value"
      },
      "targets": [
        {
          "refId": "A",
          "datasource": {
            "type": "prometheus",
            "uid": "grafanacloud-prom"
          },
          "expr": "sum(rate(crawler_tasks_total{instance=\"browser-1\", status=\"succeeded\"}[5m])) / sum(rate(crawler_tasks_total{instance=\"browser-1\"}[5m]))",
          "legendFormat": "Success Rate"
        }
      ],
      "description": "Percentage of tasks that succeed on the browser worker. ~88% is normal \u2014 some sites block or timeout."
    },
    {
      "id": 8,
      "type": "timeseries",
      "title": "Jobs Discovered \u2014 Browser",
      "datasource": {
        "type": "prometheus",
        "uid": "grafanacloud-prom"
      },
      "gridPos": {
        "h": 8,
        "w": 9,
        "x": 15,
        "y": 35
      },
      "fieldConfig": {
        "defaults": {
          "unit": "short",
          "custom": {
            "fillOpacity": 10,
            "lineWidth": 2,
            "spanNulls": true
          },
          "color": {
            "mode": "palette-classic"
          }
        },
        "overrides": []
      },
      "options": {
        "legend": {
          "displayMode": "table",
          "calcs": [
            "last"
          ]
        },
        "tooltip": {
          "mode": "multi"
        }
      },
      "targets": [
        {
          "refId": "A",
          "datasource": {
            "type": "prometheus",
            "uid": "grafanacloud-prom"
          },
          "expr": "sum by (action) (rate(crawler_monitor_jobs_discovered_total{instance=\"browser-1\"}[$__rate_interval])) * 60",
          "legendFormat": "{{action}}"
        }
      ],
      "description": "Same as HTTP but for browser-dependent monitors (api_sniffer, dom with render=true)."
    },
    {
      "id": 9,
      "type": "row",
      "title": "Queue Health",
      "collapsed": false,
      "gridPos": {
        "h": 1,
        "w": 24,
        "x": 0,
        "y": 43
      },
      "panels": []
    },
    {
      "id": 10,
      "type": "timeseries",
      "title": "Queue Depth \u2014 HTTP due now",
      "datasource": {
        "type": "prometheus",
        "uid": "grafanacloud-prom"
      },
      "gridPos": {
        "h": 8,
        "w": 5,
        "x": 0,
        "y": 44
      },
      "fieldConfig": {
        "defaults": {
          "unit": "short",
          "custom": {
            "fillOpacity": 10,
            "lineWidth": 2,
            "spanNulls": true
          },
          "color": {
            "mode": "palette-classic"
          }
        },
        "overrides": []
      },
      "options": {
        "legend": {
          "displayMode": "table",
          "calcs": [
            "last"
          ]
        },
        "tooltip": {
          "mode": "multi"
        }
      },
      "targets": [
        {
          "refId": "A",
          "datasource": {
            "type": "prometheus",
            "uid": "grafanacloud-prom"
          },
          "expr": "crawler_redis_queue_depth{instance=\"exporter\", queue=~\"ready:simple:.*:ready\"}",
          "legendFormat": "{{queue}}"
        }
      ],
      "description": "Domains with work ready to claim right now per tier. T0=first-time, T1=monitors due, T2=scrapes due. Should stay near 0 if workers keep up."
    },
    {
      "id": 11,
      "type": "timeseries",
      "title": "Total Domains \u2014 HTTP",
      "datasource": {
        "type": "prometheus",
        "uid": "grafanacloud-prom"
      },
      "gridPos": {
        "h": 8,
        "w": 5,
        "x": 5,
        "y": 44
      },
      "fieldConfig": {
        "defaults": {
          "unit": "short",
          "custom": {
            "fillOpacity": 10,
            "lineWidth": 2,
            "spanNulls": true
          },
          "color": {
            "mode": "palette-classic"
          }
        },
        "overrides": []
      },
      "options": {
        "legend": {
          "displayMode": "table",
          "calcs": [
            "last"
          ]
        },
        "tooltip": {
          "mode": "multi"
        }
      },
      "targets": [
        {
          "refId": "A",
          "datasource": {
            "type": "prometheus",
            "uid": "grafanacloud-prom"
          },
          "expr": "crawler_redis_queue_depth{instance=\"exporter\", queue=~\"ready:simple:.*:total\"}",
          "legendFormat": "{{queue}}"
        }
      ],
      "description": "All domains in each tier including future-scheduled. Shows the full queue size \u2014 work arrives as boards come due on their check_interval."
    },
    {
      "id": 12,
      "type": "timeseries",
      "title": "Queue Depth \u2014 Browser due now",
      "datasource": {
        "type": "prometheus",
        "uid": "grafanacloud-prom"
      },
      "gridPos": {
        "h": 8,
        "w": 5,
        "x": 10,
        "y": 44
      },
      "fieldConfig": {
        "defaults": {
          "unit": "short",
          "custom": {
            "fillOpacity": 10,
            "lineWidth": 2,
            "spanNulls": true
          },
          "color": {
            "mode": "palette-classic"
          }
        },
        "overrides": []
      },
      "options": {
        "legend": {
          "displayMode": "table",
          "calcs": [
            "last"
          ]
        },
        "tooltip": {
          "mode": "multi"
        }
      },
      "targets": [
        {
          "refId": "A",
          "datasource": {
            "type": "prometheus",
            "uid": "grafanacloud-prom"
          },
          "expr": "crawler_redis_queue_depth{instance=\"exporter\", queue=~\"ready:browser:.*:ready\"}",
          "legendFormat": "{{queue}}"
        }
      ],
      "description": "Browser domains with work ready now. Drains slower than HTTP due to Chromium overhead."
    },
    {
      "id": 13,
      "type": "timeseries",
      "title": "Total Domains \u2014 Browser",
      "datasource": {
        "type": "prometheus",
        "uid": "grafanacloud-prom"
      },
      "gridPos": {
        "h": 8,
        "w": 5,
        "x": 15,
        "y": 44
      },
      "fieldConfig": {
        "defaults": {
          "unit": "short",
          "custom": {
            "fillOpacity": 10,
            "lineWidth": 2,
            "spanNulls": true
          },
          "color": {
            "mode": "palette-classic"
          }
        },
        "overrides": []
      },
      "options": {
        "legend": {
          "displayMode": "table",
          "calcs": [
            "last"
          ]
        },
        "tooltip": {
          "mode": "multi"
        }
      },
      "targets": [
        {
          "refId": "A",
          "datasource": {
            "type": "prometheus",
            "uid": "grafanacloud-prom"
          },
          "expr": "crawler_redis_queue_depth{instance=\"exporter\", queue=~\"ready:browser:.*:total\"}",
          "legendFormat": "{{queue}}"
        }
      ],
      "description": "All browser domains across tiers. ~80 domains total for browser-dependent boards."
    },
    {
      "id": 907,
      "type": "stat",
      "title": "Dead-letter Depth",
      "datasource": {
        "type": "prometheus",
        "uid": "grafanacloud-prom"
      },
      "gridPos": {
        "h": 8,
        "w": 4,
        "x": 20,
        "y": 44
      },
      "fieldConfig": {
        "defaults": {
          "unit": "short",
          "thresholds": {
            "mode": "absolute",
            "steps": [
              {
                "color": "green",
                "value": null
              },
              {
                "color": "red",
                "value": 1
              }
            ]
          }
        },
        "overrides": []
      },
      "options": {
        "graphMode": "area",
        "orientation": "auto",
        "reduceOptions": {
          "calcs": [
            "lastNotNull"
          ],
          "fields": "",
          "values": false
        },
        "textMode": "auto",
        "colorMode": "value"
      },
      "targets": [
        {
          "refId": "A",
          "datasource": {
            "type": "prometheus",
            "uid": "grafanacloud-prom"
          },
          "expr": "max by (wtype) (crawler_inflight_deadletter_depth)",
          "legendFormat": "{{wtype}}"
        }
      ],
      "description": "Tasks parked in Redis deadletter:<wtype> after the inflight reaper reaches max strikes. Nonzero for >1h fires DeadletterQueueNotEmpty. Inspect with ZRANGE deadletter:simple 0 -1 WITHSCORES or ZRANGE deadletter:browser 0 -1 WITHSCORES."
    },
    {
      "id": 14,
      "type": "row",
      "title": "Latency",
      "collapsed": false,
      "gridPos": {
        "h": 1,
        "w": 24,
        "x": 0,
        "y": 52
      },
      "panels": []
    },
    {
      "id": 15,
      "type": "timeseries",
      "title": "Monitor Duration \u2014 HTTP",
      "datasource": {
        "type": "prometheus",
        "uid": "grafanacloud-prom"
      },
      "gridPos": {
        "h": 8,
        "w": 6,
        "x": 0,
        "y": 53
      },
      "fieldConfig": {
        "defaults": {
          "unit": "s",
          "custom": {
            "fillOpacity": 10,
            "lineWidth": 2,
            "spanNulls": true
          },
          "color": {
            "mode": "palette-classic"
          }
        },
        "overrides": []
      },
      "options": {
        "legend": {
          "displayMode": "table",
          "calcs": [
            "last"
          ]
        },
        "tooltip": {
          "mode": "multi"
        }
      },
      "targets": [
        {
          "refId": "A",
          "datasource": {
            "type": "prometheus",
            "uid": "grafanacloud-prom"
          },
          "expr": "histogram_quantile(0.50, sum by (le) (rate(crawler_monitor_duration_seconds_bucket{profile=\"simple\"}[$__rate_interval])))",
          "legendFormat": "p50"
        },
        {
          "refId": "B",
          "datasource": {
            "type": "prometheus",
            "uid": "grafanacloud-prom"
          },
          "expr": "histogram_quantile(0.95, sum by (le) (rate(crawler_monitor_duration_seconds_bucket{profile=\"simple\"}[$__rate_interval])))",
          "legendFormat": "p95"
        },
        {
          "refId": "C",
          "datasource": {
            "type": "prometheus",
            "uid": "grafanacloud-prom"
          },
          "expr": "histogram_quantile(0.99, sum by (le) (rate(crawler_monitor_duration_seconds_bucket{profile=\"simple\"}[$__rate_interval])))",
          "legendFormat": "p99"
        }
      ],
      "description": "p50/p95/p99 latency for HTTP monitor cycles. Most complete in 1-5s. Workday boards can take 30-60s (streaming thousands of jobs)."
    },
    {
      "id": 16,
      "type": "timeseries",
      "title": "Monitor Duration \u2014 Browser",
      "datasource": {
        "type": "prometheus",
        "uid": "grafanacloud-prom"
      },
      "gridPos": {
        "h": 8,
        "w": 6,
        "x": 6,
        "y": 53
      },
      "fieldConfig": {
        "defaults": {
          "unit": "s",
          "custom": {
            "fillOpacity": 10,
            "lineWidth": 2,
            "spanNulls": true
          },
          "color": {
            "mode": "palette-classic"
          }
        },
        "overrides": []
      },
      "options": {
        "legend": {
          "displayMode": "table",
          "calcs": [
            "last"
          ]
        },
        "tooltip": {
          "mode": "multi"
        }
      },
      "targets": [
        {
          "refId": "A",
          "datasource": {
            "type": "prometheus",
            "uid": "grafanacloud-prom"
          },
          "expr": "histogram_quantile(0.50, sum by (le) (rate(crawler_monitor_duration_seconds_bucket{profile=\"browser\"}[$__rate_interval])))",
          "legendFormat": "p50"
        },
        {
          "refId": "B",
          "datasource": {
            "type": "prometheus",
            "uid": "grafanacloud-prom"
          },
          "expr": "histogram_quantile(0.95, sum by (le) (rate(crawler_monitor_duration_seconds_bucket{profile=\"browser\"}[$__rate_interval])))",
          "legendFormat": "p95"
        },
        {
          "refId": "C",
          "datasource": {
            "type": "prometheus",
            "uid": "grafanacloud-prom"
          },
          "expr": "histogram_quantile(0.99, sum by (le) (rate(crawler_monitor_duration_seconds_bucket{profile=\"browser\"}[$__rate_interval])))",
          "legendFormat": "p99"
        }
      ],
      "description": "p50/p95/p99 for browser monitors. Higher baseline (10-30s) due to Playwright page load + rendering."
    },
    {
      "id": 17,
      "type": "timeseries",
      "title": "Scrape Duration \u2014 HTTP",
      "datasource": {
        "type": "prometheus",
        "uid": "grafanacloud-prom"
      },
      "gridPos": {
        "h": 8,
        "w": 6,
        "x": 12,
        "y": 53
      },
      "fieldConfig": {
        "defaults": {
          "unit": "s",
          "custom": {
            "fillOpacity": 10,
            "lineWidth": 2,
            "spanNulls": true
          },
          "color": {
            "mode": "palette-classic"
          }
        },
        "overrides": []
      },
      "options": {
        "legend": {
          "displayMode": "table",
          "calcs": [
            "last"
          ]
        },
        "tooltip": {
          "mode": "multi"
        }
      },
      "targets": [
        {
          "refId": "A",
          "datasource": {
            "type": "prometheus",
            "uid": "grafanacloud-prom"
          },
          "expr": "histogram_quantile(0.50, sum by (le) (rate(crawler_scrape_duration_seconds_bucket{profile=\"simple\"}[$__rate_interval])))",
          "legendFormat": "p50"
        },
        {
          "refId": "B",
          "datasource": {
            "type": "prometheus",
            "uid": "grafanacloud-prom"
          },
          "expr": "histogram_quantile(0.95, sum by (le) (rate(crawler_scrape_duration_seconds_bucket{profile=\"simple\"}[$__rate_interval])))",
          "legendFormat": "p95"
        },
        {
          "refId": "C",
          "datasource": {
            "type": "prometheus",
            "uid": "grafanacloud-prom"
          },
          "expr": "histogram_quantile(0.99, sum by (le) (rate(crawler_scrape_duration_seconds_bucket{profile=\"simple\"}[$__rate_interval])))",
          "legendFormat": "p99"
        }
      ],
      "description": "p50/p95/p99 for individual job page scrapes via HTTP. Typically 1-5s per page."
    },
    {
      "id": 18,
      "type": "timeseries",
      "title": "Scrape Duration \u2014 Browser",
      "datasource": {
        "type": "prometheus",
        "uid": "grafanacloud-prom"
      },
      "gridPos": {
        "h": 8,
        "w": 6,
        "x": 18,
        "y": 53
      },
      "fieldConfig": {
        "defaults": {
          "unit": "s",
          "custom": {
            "fillOpacity": 10,
            "lineWidth": 2,
            "spanNulls": true
          },
          "color": {
            "mode": "palette-classic"
          }
        },
        "overrides": []
      },
      "options": {
        "legend": {
          "displayMode": "table",
          "calcs": [
            "last"
          ]
        },
        "tooltip": {
          "mode": "multi"
        }
      },
      "targets": [
        {
          "refId": "A",
          "datasource": {
            "type": "prometheus",
            "uid": "grafanacloud-prom"
          },
          "expr": "histogram_quantile(0.50, sum by (le) (rate(crawler_scrape_duration_seconds_bucket{profile=\"browser\"}[$__rate_interval])))",
          "legendFormat": "p50"
        },
        {
          "refId": "B",
          "datasource": {
            "type": "prometheus",
            "uid": "grafanacloud-prom"
          },
          "expr": "histogram_quantile(0.95, sum by (le) (rate(crawler_scrape_duration_seconds_bucket{profile=\"browser\"}[$__rate_interval])))",
          "legendFormat": "p95"
        },
        {
          "refId": "C",
          "datasource": {
            "type": "prometheus",
            "uid": "grafanacloud-prom"
          },
          "expr": "histogram_quantile(0.99, sum by (le) (rate(crawler_scrape_duration_seconds_bucket{profile=\"browser\"}[$__rate_interval])))",
          "legendFormat": "p99"
        }
      ],
      "description": "p50/p95/p99 for rendered scrapes. 5-10s per page including Chromium startup."
    },
    {
      "id": 19,
      "type": "row",
      "title": "Exporter & R2",
      "collapsed": false,
      "gridPos": {
        "h": 1,
        "w": 24,
        "x": 0,
        "y": 61
      },
      "panels": []
    },
    {
      "id": 20,
      "type": "timeseries",
      "title": "Export Lag",
      "datasource": {
        "type": "prometheus",
        "uid": "grafanacloud-prom"
      },
      "gridPos": {
        "h": 8,
        "w": 6,
        "x": 0,
        "y": 62
      },
      "fieldConfig": {
        "defaults": {
          "unit": "short",
          "custom": {
            "fillOpacity": 10,
            "lineWidth": 2,
            "spanNulls": true
          },
          "color": {
            "mode": "palette-classic"
          }
        },
        "overrides": []
      },
      "options": {
        "legend": {
          "displayMode": "table",
          "calcs": [
            "last"
          ]
        },
        "tooltip": {
          "mode": "multi"
        }
      },
      "targets": [
        {
          "refId": "A",
          "datasource": {
            "type": "prometheus",
            "uid": "grafanacloud-prom"
          },
          "expr": "crawler_exporter_export_lag{instance=\"exporter\"}",
          "legendFormat": "Export Lag"
        },
        {
          "refId": "B",
          "datasource": {
            "type": "prometheus",
            "uid": "grafanacloud-prom"
          },
          "expr": "crawler_typesense_export_lag{instance=\"exporter\"}",
          "legendFormat": "Typesense Lag"
        },
        {
          "refId": "C",
          "datasource": {
            "type": "prometheus",
            "uid": "grafanacloud-prom"
          },
          "expr": "sum(rate(crawler_export_errors_total{instance=\"exporter\"}[$__rate_interval]))",
          "legendFormat": "Export Errors / s"
        }
      ]
    },
    {
      "id": 21,
      "type": "stat",
      "title": "R2 Pending",
      "datasource": {
        "type": "prometheus",
        "uid": "grafanacloud-prom"
      },
      "gridPos": {
        "h": 8,
        "w": 6,
        "x": 6,
        "y": 62
      },
      "fieldConfig": {
        "defaults": {
          "unit": "short",
          "thresholds": {
            "mode": "absolute",
            "steps": [
              {
                "color": "green",
                "value": null
              }
            ]
          }
        },
        "overrides": []
      },
      "options": {
        "graphMode": "area",
        "orientation": "auto",
        "textMode": "auto",
        "colorMode": "value"
      },
      "targets": [
        {
          "refId": "A",
          "datasource": {
            "type": "prometheus",
            "uid": "grafanacloud-prom"
          },
          "expr": "crawler_r2_pending{instance=\"exporter\"}",
          "legendFormat": "R2 Pending"
        }
      ],
      "description": "Descriptions waiting to be uploaded to R2. Should be near 0 after initial backlog clears. Only increases when description content actually changes (hash-based check)."
    },
    {
      "id": 22,
      "type": "stat",
      "title": "Exporter Staleness",
      "datasource": {
        "type": "prometheus",
        "uid": "grafanacloud-prom"
      },
      "gridPos": {
        "h": 8,
        "w": 6,
        "x": 12,
        "y": 62
      },
      "fieldConfig": {
        "defaults": {
          "unit": "s",
          "thresholds": {
            "mode": "absolute",
            "steps": [
              {
                "color": "green",
                "value": null
              },
              {
                "color": "yellow",
                "value": 30
              },
              {
                "color": "red",
                "value": 120
              }
            ]
          }
        },
        "overrides": []
      },
      "options": {
        "graphMode": "area",
        "orientation": "auto",
        "textMode": "auto",
        "colorMode": "value"
      },
      "targets": [
        {
          "refId": "A",
          "datasource": {
            "type": "prometheus",
            "uid": "grafanacloud-prom"
          },
          "expr": "time() - crawler_exporter_last_flush_ts{instance=\"exporter\"}",
          "legendFormat": "Staleness"
        }
      ],
      "description": "Seconds since last successful export tick. Should be <5s. >30s = exporter stuck or crashed."
    },
    {
      "id": 904,
      "type": "stat",
      "title": "Typesense Reconciliation Discrepancies",
      "datasource": {
        "type": "prometheus",
        "uid": "grafanacloud-prom"
      },
      "gridPos": {
        "h": 8,
        "w": 6,
        "x": 18,
        "y": 62
      },
      "fieldConfig": {
        "defaults": {
          "unit": "short",
          "thresholds": {
            "mode": "absolute",
            "steps": [
              {
                "color": "green",
                "value": null
              },
              {
                "color": "red",
                "value": 1
              }
            ]
          }
        },
        "overrides": []
      },
      "options": {
        "graphMode": "area",
        "orientation": "auto",
        "reduceOptions": {
          "calcs": [
            "lastNotNull"
          ],
          "fields": "",
          "values": false
        },
        "textMode": "auto",
        "colorMode": "value"
      },
      "targets": [
        {
          "refId": "A",
          "datasource": {
            "type": "prometheus",
            "uid": "grafanacloud-prom"
          },
          "expr": "crawler_typesense_reconciliation_discrepancies",
          "legendFormat": "discrepancies"
        }
      ]
    },
    {
      "id": 23,
      "type": "row",
      "title": "Exporter Detail",
      "collapsed": false,
      "gridPos": {
        "h": 1,
        "w": 24,
        "x": 0,
        "y": 70
      },
      "panels": []
    },
    {
      "id": 24,
      "type": "timeseries",
      "title": "Export Flush Duration",
      "datasource": {
        "type": "prometheus",
        "uid": "grafanacloud-prom"
      },
      "gridPos": {
        "h": 8,
        "w": 8,
        "x": 0,
        "y": 71
      },
      "fieldConfig": {
        "defaults": {
          "unit": "s",
          "custom": {
            "fillOpacity": 10,
            "lineWidth": 2,
            "spanNulls": true
          },
          "color": {
            "mode": "palette-classic"
          }
        },
        "overrides": []
      },
      "options": {
        "legend": {
          "displayMode": "table",
          "calcs": [
            "last"
          ]
        },
        "tooltip": {
          "mode": "multi"
        }
      },
      "targets": [
        {
          "refId": "A",
          "datasource": {
            "type": "prometheus",
            "uid": "grafanacloud-prom"
          },
          "expr": "histogram_quantile(0.50, sum by (le) (rate(crawler_exporter_flush_duration_seconds_bucket{instance=\"exporter\"}[$__rate_interval])))",
          "legendFormat": "p50"
        },
        {
          "refId": "B",
          "datasource": {
            "type": "prometheus",
            "uid": "grafanacloud-prom"
          },
          "expr": "histogram_quantile(0.95, sum by (le) (rate(crawler_exporter_flush_duration_seconds_bucket{instance=\"exporter\"}[$__rate_interval])))",
          "legendFormat": "p95"
        },
        {
          "refId": "C",
          "datasource": {
            "type": "prometheus",
            "uid": "grafanacloud-prom"
          },
          "expr": "histogram_quantile(0.95, sum by (le) (rate(crawler_typesense_export_duration_seconds_bucket{instance=\"exporter\"}[$__rate_interval])))",
          "legendFormat": "Typesense p95"
        }
      ],
      "description": "How long each exporter tick takes (p50/p95). <1s at steady state. High values during backlog catchup."
    },
    {
      "id": 25,
      "type": "timeseries",
      "title": "R2 Upload Rate",
      "datasource": {
        "type": "prometheus",
        "uid": "grafanacloud-prom"
      },
      "gridPos": {
        "h": 8,
        "w": 8,
        "x": 8,
        "y": 71
      },
      "fieldConfig": {
        "defaults": {
          "unit": "ops",
          "custom": {
            "fillOpacity": 10,
            "lineWidth": 2,
            "spanNulls": true
          },
          "color": {
            "mode": "palette-classic"
          }
        },
        "overrides": []
      },
      "options": {
        "legend": {
          "displayMode": "table",
          "calcs": [
            "last"
          ]
        },
        "tooltip": {
          "mode": "multi"
        }
      },
      "targets": [
        {
          "refId": "A",
          "datasource": {
            "type": "prometheus",
            "uid": "grafanacloud-prom"
          },
          "expr": "sum by (status) (rate(crawler_r2_uploaded_total{instance=\"drain\"}[$__rate_interval]))",
          "legendFormat": "{{status}}"
        }
      ],
      "description": "R2 PUT operations per second by the drain worker. ~40-50/s at peak. Should drop to near 0 at steady state."
    },
    {
      "id": 26,
      "type": "timeseries",
      "title": "Exporter Rows/sec",
      "datasource": {
        "type": "prometheus",
        "uid": "grafanacloud-prom"
      },
      "gridPos": {
        "h": 8,
        "w": 8,
        "x": 16,
        "y": 71
      },
      "fieldConfig": {
        "defaults": {
          "unit": "ops",
          "custom": {
            "fillOpacity": 10,
            "lineWidth": 2,
            "spanNulls": true
          },
          "color": {
            "mode": "palette-classic"
          }
        },
        "overrides": []
      },
      "options": {
        "legend": {
          "displayMode": "table",
          "calcs": [
            "last"
          ]
        },
        "tooltip": {
          "mode": "multi"
        }
      },
      "targets": [
        {
          "refId": "A",
          "datasource": {
            "type": "prometheus",
            "uid": "grafanacloud-prom"
          },
          "expr": "sum by (table) (rate(crawler_exporter_rows_exported_total{instance=\"exporter\"}[$__rate_interval]))",
          "legendFormat": "{{table}}"
        },
        {
          "refId": "B",
          "datasource": {
            "type": "prometheus",
            "uid": "grafanacloud-prom"
          },
          "expr": "sum by (status) (rate(crawler_typesense_export_docs_total{instance=\"exporter\"}[$__rate_interval]))",
          "legendFormat": "Typesense {{status}}"
        }
      ],
      "description": "Rows exported to Supabase per second. High during backlog, near 0 at steady state thanks to conditional updated_at."
    },
    {
      "id": 32,
      "type": "row",
      "title": "System",
      "collapsed": false,
      "gridPos": {
        "h": 1,
        "w": 24,
        "x": 0,
        "y": 79
      },
      "panels": []
    },
    {
      "id": 28,
      "type": "timeseries",
      "title": "Local Postgres Pool",
      "datasource": {
        "type": "prometheus",
        "uid": "grafanacloud-prom"
      },
      "gridPos": {
        "h": 8,
        "w": 6,
        "x": 0,
        "y": 80
      },
      "fieldConfig": {
        "defaults": {
          "unit": "short",
          "custom": {
            "fillOpacity": 10,
            "lineWidth": 2,
            "spanNulls": true
          },
          "color": {
            "mode": "palette-classic"
          }
        },
        "overrides": []
      },
      "options": {
        "legend": {
          "displayMode": "table",
          "calcs": [
            "last"
          ]
        },
        "tooltip": {
          "mode": "multi"
        }
      },
      "targets": [
        {
          "refId": "A",
          "datasource": {
            "type": "prometheus",
            "uid": "grafanacloud-prom"
          },
          "expr": "crawler_local_db_pool_size{instance=\"exporter\"}",
          "legendFormat": "Size"
        },
        {
          "refId": "B",
          "datasource": {
            "type": "prometheus",
            "uid": "grafanacloud-prom"
          },
          "expr": "crawler_local_db_pool_idle{instance=\"exporter\"}",
          "legendFormat": "Idle"
        },
        {
          "refId": "C",
          "datasource": {
            "type": "prometheus",
            "uid": "grafanacloud-prom"
          },
          "expr": "crawler_local_db_pool_size{instance=\"exporter\"} - crawler_local_db_pool_idle{instance=\"exporter\"}",
          "legendFormat": "In Use"
        }
      ],
      "description": "Connection pool for local Postgres (Hetzner). Size=total connections, Idle=unused, In Use=active queries."
    },
    {
      "datasource": {
        "type": "prometheus",
        "uid": "grafanacloud-prom"
      },
      "fieldConfig": {
        "defaults": {
          "custom": {
            "drawStyle": "line",
            "fillOpacity": 10,
            "lineWidth": 2,
            "spanNulls": true
          },
          "unit": "percentunit"
        }
      },
      "gridPos": {
        "h": 8,
        "w": 8,
        "x": 6,
        "y": 80
      },
      "id": 700,
      "title": "Container CPU",
      "type": "timeseries",
      "options": {
        "legend": {
          "displayMode": "table",
          "placement": "bottom",
          "calcs": [
            "last"
          ]
        }
      },
      "targets": [
        {
          "datasource": {
            "type": "prometheus",
            "uid": "grafanacloud-prom"
          },
          "expr": "rate(process_cpu_seconds_total{job=\"crawler\"}[$__rate_interval])",
          "legendFormat": "{{instance}}",
          "refId": "A"
        }
      ],
      "description": "Per-container CPU usage. Each HTTP worker should be near 100% (1 core). Browser worker uses up to 300% (3 cores)."
    },
    {
      "datasource": {
        "type": "prometheus",
        "uid": "grafanacloud-prom"
      },
      "fieldConfig": {
        "defaults": {
          "custom": {
            "drawStyle": "line",
            "fillOpacity": 10,
            "lineWidth": 2,
            "spanNulls": true
          },
          "unit": "bytes"
        }
      },
      "gridPos": {
        "h": 8,
        "w": 8,
        "x": 14,
        "y": 80
      },
      "id": 701,
      "title": "Container Memory",
      "type": "timeseries",
      "options": {
        "legend": {
          "displayMode": "table",
          "placement": "bottom",
          "calcs": [
            "last"
          ]
        }
      },
      "targets": [
        {
          "datasource": {
            "type": "prometheus",
            "uid": "grafanacloud-prom"
          },
          "expr": "process_resident_memory_bytes{job=\"crawler\"}",
          "legendFormat": "{{instance}}",
          "refId": "A"
        }
      ],
      "description": "Per-container RSS memory. HTTP workers ~150-300MB. Browser worker 1-2GB (Chromium). Watch for growth patterns indicating leaks."
    },
    {
      "datasource": {
        "type": "prometheus",
        "uid": "grafanacloud-prom"
      },
      "fieldConfig": {
        "defaults": {
          "custom": {
            "drawStyle": "line",
            "fillOpacity": 10,
            "lineWidth": 2,
            "spanNulls": true
          },
          "unit": "bytes"
        }
      },
      "gridPos": {
        "h": 8,
        "w": 8,
        "x": 0,
        "y": 88
      },
      "id": 704,
      "title": "Disk Available",
      "type": "timeseries",
      "options": {
        "legend": {
          "displayMode": "table",
          "placement": "bottom",
          "calcs": [
            "last"
          ]
        }
      },
      "targets": [
        {
          "datasource": {
            "type": "prometheus",
            "uid": "grafanacloud-prom"
          },
          "expr": "node_filesystem_avail_bytes{job=\"integrations/unix\", mountpoint=\"/\"}",
          "legendFormat": "/",
          "refId": "A"
        },
        {
          "datasource": {
            "type": "prometheus",
            "uid": "grafanacloud-prom"
          },
          "expr": "node_filesystem_avail_bytes{job=\"integrations/unix\", mountpoint=~\"/mnt/.*\"}",
          "legendFormat": "{{mountpoint}}",
          "refId": "B"
        }
      ],
      "description": "Free disk space on root (/) and data mount (/mnt). Postgres data grows over time."
    },
    {
      "datasource": {
        "type": "prometheus",
        "uid": "grafanacloud-prom"
      },
      "fieldConfig": {
        "defaults": {
          "custom": {
            "drawStyle": "line",
            "fillOpacity": 10,
            "lineWidth": 2,
            "spanNulls": true
          },
          "unit": "Bps"
        }
      },
      "gridPos": {
        "h": 8,
        "w": 8,
        "x": 8,
        "y": 88
      },
      "id": 705,
      "title": "Network I/O",
      "type": "timeseries",
      "options": {
        "legend": {
          "displayMode": "table",
          "placement": "bottom",
          "calcs": [
            "last"
          ]
        }
      },
      "targets": [
        {
          "datasource": {
            "type": "prometheus",
            "uid": "grafanacloud-prom"
          },
          "expr": "sum(rate(node_network_receive_bytes_total{job=\"integrations/unix\", device!~\"lo|veth.*|docker.*|br-.*\"}[$__rate_interval]))",
          "legendFormat": "Receive",
          "refId": "A"
        },
        {
          "datasource": {
            "type": "prometheus",
            "uid": "grafanacloud-prom"
          },
          "expr": "sum(rate(node_network_transmit_bytes_total{job=\"integrations/unix\", device!~\"lo|veth.*|docker.*|br-.*\"}[$__rate_interval]))",
          "legendFormat": "Transmit",
          "refId": "B"
        }
      ],
      "description": "Machine network throughput. Receive=crawled pages from career sites. Transmit=R2 uploads + Supabase exports."
    }
  ]
}
