{
	"_type": "job-comparison",
	"company": "Deel",
	"normalizedTitle": "dutch speaking field marketing manager dach benelux",
	"careerTitle": "Dutch Speaking Field Marketing Manager | DACH & Benelux",
	"careerPageFirstSeen": "2026-03-24",
	"careerPageDatePosted": "2026-03-24",
	"effectiveCareerDate": "2026-03-24",
	"verdict": "career_only",
	"location": "UK",
	"department": "S&M",
	"careerSnapshotUrl": "https://web.archive.org/web/20260401234008/https://api.ashbyhq.com/posting-api/job-board/deel"
}