{
	"_type": "job-comparison",
	"company": "Notion",
	"normalizedTitle": "customer success manager dedicated dach",
	"careerTitle": "Customer Success Manager, Dedicated, DACH",
	"careerPageFirstSeen": "2026-01-27",
	"careerPageDatePosted": "2026-01-27",
	"effectiveCareerDate": "2026-01-27",
	"verdict": "career_only",
	"location": "Dublin, Ireland",
	"department": "Customer Success",
	"careerSnapshotUrl": "https://web.archive.org/web/20260401221609/https://api.ashbyhq.com/posting-api/job-board/notion"
}